dowker/__init__.py
dowker/simplex_tree.py
dowker/sink.py
dowker-0.0.1.dist-info/METADATA
dowker-0.0.1.dist-info/WHEEL
dowker-0.0.1.dist-info/top_level.txt
dowker-0.0.1.dist-info/RECORD
